arkouda/__init__.py
arkouda/client.py
arkouda/dtypes.py
arkouda/groupbyclass.py
arkouda/numeric.py
arkouda/pdarrayIO.py
arkouda/pdarrayclass.py
arkouda/pdarraycreation.py
arkouda/pdarraysetops.py
arkouda/sorting.py
arkouda/strings.py
arkouda-2019.12.10.dist-info/METADATA
arkouda-2019.12.10.dist-info/RECORD
arkouda-2019.12.10.dist-info/WHEEL
arkouda-2019.12.10.dist-info/top_level.txt
