Metadata-Version: 2.1
Name: arkouda
Version: 2019.12.10
Summary: Parallel, distributed NumPy-like arrays backed by Chapel
Home-page: https://github.com/mhmerrill/arkouda
Author: U.S. Government
Author-email: 
License: UNKNOWN
Project-URL: Bug Reports, https://github.com/mhmerrill/arkouda/issues
Project-URL: Source, https://github.com/mhmerrill/arkouda
Project-URL: Chapel, https://chapel-lang.org
Keywords: HPC workflow exploratory analysis parallel distribute arrays Chapel
Platform: UNKNOWN
Classifier: Development Status :: 3 - Alpha
Classifier: Intended Audience :: Science/Research
Classifier: Topic :: Scientific/Engineering
Classifier: License :: OSI Approved :: MIT License
Classifier: Programming Language :: Python :: 3
Classifier: Programming Language :: Python :: 3.6
Classifier: Programming Language :: Python :: 3.7
Requires-Python: >=3.6
Provides-Extra: test
Provides-Extra: doc
Provides-Extra: dev
Requires-Dist: numpy
Requires-Dist: zmq
Provides-Extra: dev
Requires-Dist: h5py; extra == 'dev'
Provides-Extra: doc
Requires-Dist: Sphinx; extra == 'doc'
Requires-Dist: sphinx-argparse; extra == 'doc'
Provides-Extra: test
Requires-Dist: pandas; extra == 'test'
